{
    "change_points": [
        {
            "date": "2002-02-11 18:14:17",
            "SQALE_INDEX": 1209.0
        },
        {
            "date": "2002-02-12 21:34:35",
            "SQALE_INDEX": 2180.0
        },
        {
            "date": "2002-02-13 16:00:39",
            "SQALE_INDEX": 2712.0
        },
        {
            "date": "2002-02-13 17:03:09",
            "SQALE_INDEX": 2845.0
        },
        {
            "date": "2002-02-15 18:25:06",
            "SQALE_INDEX": 3105.0
        },
        {
            "date": "2002-02-19 15:40:58",
            "SQALE_INDEX": 3105.0
        },
        {
            "date": "2002-03-07 02:46:04",
            "SQALE_INDEX": 3340.0
        },
        {
            "date": "2002-03-07 03:57:13",
            "SQALE_INDEX": 3339.0
        },
        {
            "date": "2002-04-24 11:59:13",
            "SQALE_INDEX": 3240.0
        },
        {
            "date": "2002-04-24 13:03:03",
            "SQALE_INDEX": 3427.0
        },
        {
            "date": "2002-04-25 16:47:07",
            "SQALE_INDEX": 3432.0
        },
        {
            "date": "2002-04-25 18:14:09",
            "SQALE_INDEX": 3540.0
        },
        {
            "date": "2002-04-25 18:58:47",
            "SQALE_INDEX": 3600.0
        },
        {
            "date": "2002-04-25 19:25:08",
            "SQALE_INDEX": 3643.0
        },
        {
            "date": "2002-04-26 04:29:41",
            "SQALE_INDEX": 3735.0
        },
        {
            "date": "2002-04-26 07:56:10",
            "SQALE_INDEX": 4100.0
        },
        {
            "date": "2002-04-26 11:28:55",
            "SQALE_INDEX": 3874.0
        },
        {
            "date": "2002-04-26 12:20:12",
            "SQALE_INDEX": 3991.0
        },
        {
            "date": "2002-05-15 06:25:50",
            "SQALE_INDEX": 6055.0
        },
        {
            "date": "2002-05-15 16:21:06",
            "SQALE_INDEX": 6122.0
        },
        {
            "date": "2002-05-16 16:29:55",
            "SQALE_INDEX": 6341.0
        },
        {
            "date": "2002-05-16 18:20:35",
            "SQALE_INDEX": 5968.0
        },
        {
            "date": "2002-05-17 15:18:15",
            "SQALE_INDEX": 5841.0
        },
        {
            "date": "2002-05-20 10:09:28",
            "SQALE_INDEX": 6226.0
        },
        {
            "date": "2002-05-21 16:53:26",
            "SQALE_INDEX": 5995.0
        },
        {
            "date": "2002-05-25 18:27:22",
            "SQALE_INDEX": 6848.0
        },
        {
            "date": "2002-05-30 08:13:50",
            "SQALE_INDEX": 7054.0
        },
        {
            "date": "2002-05-30 12:15:25",
            "SQALE_INDEX": 7215.0
        },
        {
            "date": "2002-05-30 14:27:07",
            "SQALE_INDEX": 7233.0
        },
        {
            "date": "2002-05-30 14:58:30",
            "SQALE_INDEX": 7239.0
        },
        {
            "date": "2002-06-01 10:21:14",
            "SQALE_INDEX": 7192.0
        },
        {
            "date": "2002-06-02 17:29:02",
            "SQALE_INDEX": 7426.0
        },
        {
            "date": "2002-06-05 07:12:58",
            "SQALE_INDEX": 8063.0
        },
        {
            "date": "2002-06-05 17:05:21",
            "SQALE_INDEX": 8068.0
        },
        {
            "date": "2002-06-05 17:14:38",
            "SQALE_INDEX": 8068.0
        },
        {
            "date": "2002-06-05 18:03:38",
            "SQALE_INDEX": 8070.0
        },
        {
            "date": "2002-06-06 07:13:41",
            "SQALE_INDEX": 8119.0
        },
        {
            "date": "2002-06-07 09:00:36",
            "SQALE_INDEX": 8219.0
        },
        {
            "date": "2002-06-07 09:36:11",
            "SQALE_INDEX": 8391.0
        },
        {
            "date": "2002-06-08 16:45:10",
            "SQALE_INDEX": 8071.0
        },
        {
            "date": "2002-06-11 21:41:11",
            "SQALE_INDEX": 9001.0
        },
        {
            "date": "2002-06-11 22:59:22",
            "SQALE_INDEX": 8973.0
        },
        {
            "date": "2002-06-12 04:32:28",
            "SQALE_INDEX": 8981.0
        },
        {
            "date": "2002-06-12 06:07:29",
            "SQALE_INDEX": 8677.0
        },
        {
            "date": "2002-06-12 13:54:47",
            "SQALE_INDEX": 8674.0
        },
        {
            "date": "2002-06-12 17:09:41",
            "SQALE_INDEX": 8757.0
        },
        {
            "date": "2002-06-12 19:28:08",
            "SQALE_INDEX": 8879.0
        },
        {
            "date": "2002-06-12 22:09:46",
            "SQALE_INDEX": 9244.0
        },
        {
            "date": "2002-06-13 08:16:47",
            "SQALE_INDEX": 9071.0
        },
        {
            "date": "2002-06-13 21:31:14",
            "SQALE_INDEX": 9121.0
        },
        {
            "date": "2002-06-14 04:04:12",
            "SQALE_INDEX": 9166.0
        },
        {
            "date": "2002-06-14 06:53:03",
            "SQALE_INDEX": 9159.0
        },
        {
            "date": "2002-06-14 10:24:14",
            "SQALE_INDEX": 9333.0
        },
        {
            "date": "2002-06-14 14:13:48",
            "SQALE_INDEX": 9321.0
        },
        {
            "date": "2002-06-17 10:15:24",
            "SQALE_INDEX": 9348.0
        },
        {
            "date": "2002-06-18 08:31:02",
            "SQALE_INDEX": 9530.0
        },
        {
            "date": "2002-06-18 12:27:24",
            "SQALE_INDEX": 9611.0
        },
        {
            "date": "2002-06-18 12:30:10",
            "SQALE_INDEX": 9793.0
        },
        {
            "date": "2002-06-18 18:36:43",
            "SQALE_INDEX": 10792.0
        },
        {
            "date": "2002-06-19 17:14:01",
            "SQALE_INDEX": 10812.0
        },
        {
            "date": "2002-06-20 14:30:43",
            "SQALE_INDEX": 11576.0
        },
        {
            "date": "2002-06-21 02:57:17",
            "SQALE_INDEX": 11171.0
        },
        {
            "date": "2002-06-21 16:57:17",
            "SQALE_INDEX": 11722.0
        },
        {
            "date": "2002-06-22 16:55:51",
            "SQALE_INDEX": 12325.0
        },
        {
            "date": "2002-06-23 01:29:34",
            "SQALE_INDEX": 12272.0
        },
        {
            "date": "2002-06-24 11:17:09",
            "SQALE_INDEX": 13799.0
        },
        {
            "date": "2002-06-25 19:12:29",
            "SQALE_INDEX": 13344.0
        },
        {
            "date": "2002-06-25 20:43:30",
            "SQALE_INDEX": 13407.0
        },
        {
            "date": "2002-06-25 21:02:25",
            "SQALE_INDEX": 13412.0
        },
        {
            "date": "2002-06-26 09:17:44",
            "SQALE_INDEX": 13519.0
        },
        {
            "date": "2002-06-26 09:43:31",
            "SQALE_INDEX": 13539.0
        },
        {
            "date": "2002-06-26 11:46:45",
            "SQALE_INDEX": 13732.0
        },
        {
            "date": "2002-06-26 13:09:09",
            "SQALE_INDEX": 12841.0
        },
        {
            "date": "2002-06-26 14:50:44",
            "SQALE_INDEX": 12769.0
        },
        {
            "date": "2002-06-27 14:09:15",
            "SQALE_INDEX": 12989.0
        },
        {
            "date": "2002-06-27 14:16:24",
            "SQALE_INDEX": 13629.0
        },
        {
            "date": "2002-06-27 21:08:08",
            "SQALE_INDEX": 13641.0
        },
        {
            "date": "2002-06-28 03:30:24",
            "SQALE_INDEX": 13688.0
        },
        {
            "date": "2002-07-07 19:38:11",
            "SQALE_INDEX": 14786.0
        },
        {
            "date": "2002-07-09 21:13:07",
            "SQALE_INDEX": 14806.0
        },
        {
            "date": "2002-07-10 16:12:17",
            "SQALE_INDEX": 14791.0
        },
        {
            "date": "2002-07-10 18:53:50",
            "SQALE_INDEX": 14835.0
        },
        {
            "date": "2002-07-13 00:49:45",
            "SQALE_INDEX": 15086.0
        },
        {
            "date": "2002-07-15 12:13:20",
            "SQALE_INDEX": 15085.0
        },
        {
            "date": "2002-07-15 15:06:19",
            "SQALE_INDEX": 15112.0
        },
        {
            "date": "2002-07-15 16:18:15",
            "SQALE_INDEX": 15200.0
        },
        {
            "date": "2002-07-15 16:57:44",
            "SQALE_INDEX": 15380.0
        },
        {
            "date": "2002-07-15 21:31:34",
            "SQALE_INDEX": 15485.0
        },
        {
            "date": "2002-07-15 21:34:53",
            "SQALE_INDEX": 15485.0
        },
        {
            "date": "2002-07-15 23:24:32",
            "SQALE_INDEX": 15590.0
        },
        {
            "date": "2002-07-16 05:43:32",
            "SQALE_INDEX": 16002.0
        },
        {
            "date": "2002-07-17 17:38:25",
            "SQALE_INDEX": 16150.0
        },
        {
            "date": "2002-07-19 22:18:10",
            "SQALE_INDEX": 15882.0
        },
        {
            "date": "2002-07-19 22:19:32",
            "SQALE_INDEX": 15972.0
        },
        {
            "date": "2002-07-19 23:05:21",
            "SQALE_INDEX": 16072.0
        },
        {
            "date": "2002-07-20 07:55:16",
            "SQALE_INDEX": 16244.0
        },
        {
            "date": "2002-07-20 08:12:04",
            "SQALE_INDEX": 16487.0
        },
        {
            "date": "2002-07-22 07:16:52",
            "SQALE_INDEX": 16614.0
        },
        {
            "date": "2002-07-22 10:49:11",
            "SQALE_INDEX": 16665.0
        },
        {
            "date": "2002-07-22 14:05:29",
            "SQALE_INDEX": 16692.0
        },
        {
            "date": "2002-07-23 12:52:44",
            "SQALE_INDEX": 17232.0
        },
        {
            "date": "2002-07-23 15:23:30",
            "SQALE_INDEX": 17492.0
        },
        {
            "date": "2002-07-24 17:34:43",
            "SQALE_INDEX": 17646.0
        },
        {
            "date": "2002-07-25 01:51:21",
            "SQALE_INDEX": 18211.0
        },
        {
            "date": "2002-07-30 17:57:20",
            "SQALE_INDEX": 18701.0
        },
        {
            "date": "2002-07-31 11:19:21",
            "SQALE_INDEX": 19195.0
        },
        {
            "date": "2002-08-01 09:53:19",
            "SQALE_INDEX": 18771.0
        },
        {
            "date": "2002-08-09 15:46:55",
            "SQALE_INDEX": 18781.0
        },
        {
            "date": "2002-08-09 15:48:48",
            "SQALE_INDEX": 18800.0
        },
        {
            "date": "2002-08-09 15:49:11",
            "SQALE_INDEX": 18820.0
        },
        {
            "date": "2002-08-09 15:50:14",
            "SQALE_INDEX": 19307.0
        },
        {
            "date": "2002-08-09 18:42:21",
            "SQALE_INDEX": 19591.0
        },
        {
            "date": "2002-08-09 19:11:56",
            "SQALE_INDEX": 19606.0
        },
        {
            "date": "2002-08-11 11:44:36",
            "SQALE_INDEX": 19068.0
        },
        {
            "date": "2002-08-12 19:10:36",
            "SQALE_INDEX": 18828.0
        },
        {
            "date": "2002-08-15 07:56:11",
            "SQALE_INDEX": 18875.0
        },
        {
            "date": "2002-08-19 07:15:39",
            "SQALE_INDEX": 18891.0
        },
        {
            "date": "2002-08-19 21:38:56",
            "SQALE_INDEX": 19023.0
        },
        {
            "date": "2002-08-19 21:42:03",
            "SQALE_INDEX": 19055.0
        },
        {
            "date": "2002-08-20 17:26:10",
            "SQALE_INDEX": 19436.0
        },
        {
            "date": "2002-08-27 14:04:44",
            "SQALE_INDEX": 19932.0
        },
        {
            "date": "2002-08-28 08:58:00",
            "SQALE_INDEX": 20555.0
        },
        {
            "date": "2002-08-28 09:19:30",
            "SQALE_INDEX": 21048.0
        },
        {
            "date": "2002-09-05 13:36:44",
            "SQALE_INDEX": 21143.0
        },
        {
            "date": "2002-09-05 16:41:31",
            "SQALE_INDEX": 21195.0
        },
        {
            "date": "2002-09-05 16:42:47",
            "SQALE_INDEX": 21205.0
        },
        {
            "date": "2002-09-05 16:43:29",
            "SQALE_INDEX": 21230.0
        },
        {
            "date": "2002-09-05 16:44:38",
            "SQALE_INDEX": 21250.0
        },
        {
            "date": "2002-09-17 15:28:24",
            "SQALE_INDEX": 21337.0
        },
        {
            "date": "2002-09-18 18:47:17",
            "SQALE_INDEX": 21270.0
        },
        {
            "date": "2002-09-23 12:35:42",
            "SQALE_INDEX": 21514.0
        },
        {
            "date": "2002-09-24 11:39:50",
            "SQALE_INDEX": 21534.0
        },
        {
            "date": "2002-09-24 16:48:54",
            "SQALE_INDEX": 21910.0
        },
        {
            "date": "2002-09-24 17:30:33",
            "SQALE_INDEX": 22443.0
        },
        {
            "date": "2002-09-25 08:37:51",
            "SQALE_INDEX": 22562.0
        },
        {
            "date": "2002-09-25 16:26:16",
            "SQALE_INDEX": 24480.0
        },
        {
            "date": "2002-09-25 18:36:59",
            "SQALE_INDEX": 24727.0
        },
        {
            "date": "2002-09-26 12:28:21",
            "SQALE_INDEX": 24733.0
        },
        {
            "date": "2002-09-26 18:07:37",
            "SQALE_INDEX": 24867.0
        },
        {
            "date": "2002-09-26 18:35:23",
            "SQALE_INDEX": 24899.0
        },
        {
            "date": "2002-09-26 18:39:06",
            "SQALE_INDEX": 24824.0
        },
        {
            "date": "2002-09-27 02:07:54",
            "SQALE_INDEX": 25656.0
        },
        {
            "date": "2002-09-27 14:20:13",
            "SQALE_INDEX": 25596.0
        },
        {
            "date": "2002-09-30 08:05:45",
            "SQALE_INDEX": 25747.0
        },
        {
            "date": "2002-09-30 17:38:16",
            "SQALE_INDEX": 25532.0
        },
        {
            "date": "2002-09-30 17:40:16",
            "SQALE_INDEX": 25557.0
        },
        {
            "date": "2002-09-30 17:52:28",
            "SQALE_INDEX": 26159.0
        },
        {
            "date": "2002-10-01 16:11:24",
            "SQALE_INDEX": 26159.0
        },
        {
            "date": "2002-10-01 16:43:56",
            "SQALE_INDEX": 26164.0
        },
        {
            "date": "2002-10-01 16:45:23",
            "SQALE_INDEX": 26164.0
        },
        {
            "date": "2002-10-02 11:03:38",
            "SQALE_INDEX": 26308.0
        },
        {
            "date": "2002-10-02 16:07:27",
            "SQALE_INDEX": 26427.0
        },
        {
            "date": "2002-10-04 11:28:20",
            "SQALE_INDEX": 26264.0
        },
        {
            "date": "2002-10-05 03:37:24",
            "SQALE_INDEX": 26286.0
        },
        {
            "date": "2002-10-08 11:26:00",
            "SQALE_INDEX": 26313.0
        },
        {
            "date": "2002-10-09 07:04:29",
            "SQALE_INDEX": 26317.0
        },
        {
            "date": "2002-10-09 21:03:08",
            "SQALE_INDEX": 26494.0
        },
        {
            "date": "2002-10-10 14:50:21",
            "SQALE_INDEX": 26635.0
        },
        {
            "date": "2002-10-10 22:19:19",
            "SQALE_INDEX": 27091.0
        },
        {
            "date": "2002-10-14 19:17:02",
            "SQALE_INDEX": 26956.0
        },
        {
            "date": "2002-10-14 21:31:15",
            "SQALE_INDEX": 27008.0
        },
        {
            "date": "2002-10-16 16:18:42",
            "SQALE_INDEX": 27557.0
        },
        {
            "date": "2002-10-16 18:17:58",
            "SQALE_INDEX": 28187.0
        },
        {
            "date": "2002-10-16 22:30:14",
            "SQALE_INDEX": 28399.0
        },
        {
            "date": "2002-10-16 22:58:29",
            "SQALE_INDEX": 28569.0
        },
        {
            "date": "2002-10-17 07:51:31",
            "SQALE_INDEX": 28696.0
        },
        {
            "date": "2002-10-17 17:27:38",
            "SQALE_INDEX": 28726.0
        },
        {
            "date": "2002-10-22 15:13:43",
            "SQALE_INDEX": 29120.0
        },
        {
            "date": "2002-10-22 15:29:12",
            "SQALE_INDEX": 29294.0
        },
        {
            "date": "2002-10-22 21:57:47",
            "SQALE_INDEX": 29537.0
        },
        {
            "date": "2002-10-23 15:39:40",
            "SQALE_INDEX": 29732.0
        },
        {
            "date": "2002-10-23 23:54:16",
            "SQALE_INDEX": 29805.0
        },
        {
            "date": "2002-10-24 06:59:54",
            "SQALE_INDEX": 29956.0
        },
        {
            "date": "2002-10-26 09:38:59",
            "SQALE_INDEX": 29961.0
        },
        {
            "date": "2002-10-29 09:10:15",
            "SQALE_INDEX": 29948.0
        },
        {
            "date": "2002-10-30 11:54:12",
            "SQALE_INDEX": 31498.0
        },
        {
            "date": "2002-10-30 19:10:48",
            "SQALE_INDEX": 31518.0
        },
        {
            "date": "2002-10-30 19:13:42",
            "SQALE_INDEX": 33687.0
        },
        {
            "date": "2002-10-30 19:16:34",
            "SQALE_INDEX": 33687.0
        },
        {
            "date": "2002-10-30 19:29:15",
            "SQALE_INDEX": 33679.0
        },
        {
            "date": "2002-10-30 19:30:47",
            "SQALE_INDEX": 33789.0
        },
        {
            "date": "2002-10-31 15:08:10",
            "SQALE_INDEX": 33927.0
        },
        {
            "date": "2002-11-05 13:06:13",
            "SQALE_INDEX": 34029.0
        },
        {
            "date": "2002-11-08 18:27:52",
            "SQALE_INDEX": 34058.0
        },
        {
            "date": "2002-11-11 11:49:06",
            "SQALE_INDEX": 34106.0
        },
        {
            "date": "2002-11-11 18:57:57",
            "SQALE_INDEX": 34392.0
        },
        {
            "date": "2002-11-12 08:39:50",
            "SQALE_INDEX": 34402.0
        },
        {
            "date": "2002-11-13 12:59:35",
            "SQALE_INDEX": 34526.0
        },
        {
            "date": "2002-11-13 19:35:15",
            "SQALE_INDEX": 34648.0
        },
        {
            "date": "2002-11-18 12:35:08",
            "SQALE_INDEX": 34518.0
        },
        {
            "date": "2002-11-20 22:20:21",
            "SQALE_INDEX": 34774.0
        },
        {
            "date": "2002-11-21 12:41:23",
            "SQALE_INDEX": 34874.0
        },
        {
            "date": "2002-11-25 14:29:07",
            "SQALE_INDEX": 34888.0
        },
        {
            "date": "2002-11-26 08:35:31",
            "SQALE_INDEX": 34790.0
        },
        {
            "date": "2002-11-27 13:07:48",
            "SQALE_INDEX": 34900.0
        },
        {
            "date": "2002-11-27 16:46:10",
            "SQALE_INDEX": 35253.0
        },
        {
            "date": "2002-11-27 17:21:16",
            "SQALE_INDEX": 35669.0
        },
        {
            "date": "2002-11-28 00:22:23",
            "SQALE_INDEX": 35984.0
        },
        {
            "date": "2002-11-28 08:35:48",
            "SQALE_INDEX": 36146.0
        },
        {
            "date": "2002-11-28 13:16:08",
            "SQALE_INDEX": 36290.0
        },
        {
            "date": "2002-11-29 15:53:10",
            "SQALE_INDEX": 36541.0
        },
        {
            "date": "2002-12-09 15:18:26",
            "SQALE_INDEX": 36945.0
        },
        {
            "date": "2002-12-11 12:41:02",
            "SQALE_INDEX": 35969.0
        },
        {
            "date": "2002-12-13 18:08:31",
            "SQALE_INDEX": 35979.0
        },
        {
            "date": "2002-12-16 10:51:06",
            "SQALE_INDEX": 36047.0
        },
        {
            "date": "2002-12-18 15:27:50",
            "SQALE_INDEX": 37007.0
        },
        {
            "date": "2002-12-19 14:46:00",
            "SQALE_INDEX": 37162.0
        },
        {
            "date": "2002-12-19 15:03:51",
            "SQALE_INDEX": 37202.0
        },
        {
            "date": "2002-12-24 04:50:19",
            "SQALE_INDEX": 37331.0
        },
        {
            "date": "2002-12-31 01:31:14",
            "SQALE_INDEX": 37333.0
        },
        {
            "date": "2002-12-31 11:11:34",
            "SQALE_INDEX": 36607.0
        },
        {
            "date": "2003-01-05 01:26:25",
            "SQALE_INDEX": 32877.0
        },
        {
            "date": "2003-01-05 08:11:36",
            "SQALE_INDEX": 31590.0
        },
        {
            "date": "2003-01-07 03:33:34",
            "SQALE_INDEX": 31662.0
        },
        {
            "date": "2003-01-07 14:42:59",
            "SQALE_INDEX": 31752.0
        },
        {
            "date": "2003-01-07 16:11:19",
            "SQALE_INDEX": 32389.0
        },
        {
            "date": "2003-01-11 08:59:46",
            "SQALE_INDEX": 31802.0
        },
        {
            "date": "2003-01-11 13:27:29",
            "SQALE_INDEX": 31990.0
        },
        {
            "date": "2003-01-14 04:01:01",
            "SQALE_INDEX": 32427.0
        },
        {
            "date": "2003-01-15 06:42:48",
            "SQALE_INDEX": 31458.0
        },
        {
            "date": "2003-01-15 14:58:05",
            "SQALE_INDEX": 31860.0
        },
        {
            "date": "2003-01-15 23:46:46",
            "SQALE_INDEX": 31311.0
        },
        {
            "date": "2003-01-15 23:56:45",
            "SQALE_INDEX": 32178.0
        },
        {
            "date": "2003-01-16 16:22:02",
            "SQALE_INDEX": 32023.0
        },
        {
            "date": "2003-01-16 22:41:33",
            "SQALE_INDEX": 32128.0
        },
        {
            "date": "2003-01-16 22:57:13",
            "SQALE_INDEX": 32325.0
        },
        {
            "date": "2003-01-16 23:11:13",
            "SQALE_INDEX": 32380.0
        },
        {
            "date": "2003-01-18 06:35:27",
            "SQALE_INDEX": 32397.0
        },
        {
            "date": "2003-01-19 06:03:12",
            "SQALE_INDEX": 32400.0
        },
        {
            "date": "2003-01-19 06:17:10",
            "SQALE_INDEX": 33086.0
        },
        {
            "date": "2003-01-22 09:19:30",
            "SQALE_INDEX": 33298.0
        },
        {
            "date": "2003-01-23 22:25:01",
            "SQALE_INDEX": 33585.0
        },
        {
            "date": "2003-01-24 01:44:21",
            "SQALE_INDEX": 33565.0
        },
        {
            "date": "2003-01-24 01:57:55",
            "SQALE_INDEX": 33660.0
        },
        {
            "date": "2003-01-24 05:26:14",
            "SQALE_INDEX": 33696.0
        },
        {
            "date": "2003-01-24 05:54:37",
            "SQALE_INDEX": 33646.0
        },
        {
            "date": "2003-01-24 06:41:23",
            "SQALE_INDEX": 33596.0
        },
        {
            "date": "2003-01-24 10:04:33",
            "SQALE_INDEX": 31719.0
        },
        {
            "date": "2003-01-26 03:45:09",
            "SQALE_INDEX": 32170.0
        },
        {
            "date": "2003-01-26 04:04:36",
            "SQALE_INDEX": 32352.0
        },
        {
            "date": "2003-01-26 08:44:58",
            "SQALE_INDEX": 32601.0
        },
        {
            "date": "2003-02-07 12:53:55",
            "SQALE_INDEX": 32833.0
        },
        {
            "date": "2003-02-11 15:29:07",
            "SQALE_INDEX": 31629.0
        },
        {
            "date": "2003-02-19 07:24:40",
            "SQALE_INDEX": 31626.0
        },
        {
            "date": "2003-02-19 07:45:07",
            "SQALE_INDEX": 31723.0
        },
        {
            "date": "2003-02-20 15:57:56",
            "SQALE_INDEX": 31733.0
        },
        {
            "date": "2003-02-25 23:26:15",
            "SQALE_INDEX": 32198.0
        },
        {
            "date": "2003-03-06 11:50:41",
            "SQALE_INDEX": 33863.0
        },
        {
            "date": "2003-03-07 12:21:28",
            "SQALE_INDEX": 33926.0
        },
        {
            "date": "2003-03-07 13:17:54",
            "SQALE_INDEX": 33928.0
        },
        {
            "date": "2003-03-08 10:13:34",
            "SQALE_INDEX": 34020.0
        },
        {
            "date": "2003-06-25 02:57:55",
            "SQALE_INDEX": 34448.0
        },
        {
            "date": "2003-07-11 06:27:07",
            "SQALE_INDEX": 34421.0
        },
        {
            "date": "2003-07-28 00:34:11",
            "SQALE_INDEX": 34620.0
        },
        {
            "date": "2003-07-28 00:43:23",
            "SQALE_INDEX": 34622.0
        },
        {
            "date": "2003-09-04 01:32:45",
            "SQALE_INDEX": 34730.0
        },
        {
            "date": "2004-02-05 22:32:30",
            "SQALE_INDEX": 34929.0
        },
        {
            "date": "2004-02-25 01:32:00",
            "SQALE_INDEX": 34994.0
        },
        {
            "date": "2004-06-21 11:20:11",
            "SQALE_INDEX": 36299.0
        },
        {
            "date": "2004-08-12 04:25:43",
            "SQALE_INDEX": 36529.0
        },
        {
            "date": "2004-08-12 04:58:41",
            "SQALE_INDEX": 36561.0
        },
        {
            "date": "2004-08-12 07:02:14",
            "SQALE_INDEX": 36630.0
        },
        {
            "date": "2004-08-16 01:59:32",
            "SQALE_INDEX": 36660.0
        },
        {
            "date": "2004-08-29 11:47:53",
            "SQALE_INDEX": 36665.0
        },
        {
            "date": "2004-08-29 13:25:42",
            "SQALE_INDEX": 36475.0
        },
        {
            "date": "2004-09-01 05:32:17",
            "SQALE_INDEX": 36903.0
        },
        {
            "date": "2004-09-02 04:01:24",
            "SQALE_INDEX": 37077.0
        },
        {
            "date": "2004-09-02 04:07:17",
            "SQALE_INDEX": 37043.0
        },
        {
            "date": "2004-09-02 07:17:19",
            "SQALE_INDEX": 37013.0
        },
        {
            "date": "2004-09-05 15:42:36",
            "SQALE_INDEX": 37181.0
        },
        {
            "date": "2004-09-06 00:21:10",
            "SQALE_INDEX": 37197.0
        },
        {
            "date": "2004-09-06 00:41:07",
            "SQALE_INDEX": 37181.0
        },
        {
            "date": "2004-09-06 02:51:06",
            "SQALE_INDEX": 37261.0
        },
        {
            "date": "2004-09-06 03:14:14",
            "SQALE_INDEX": 37527.0
        },
        {
            "date": "2004-09-06 03:17:48",
            "SQALE_INDEX": 37452.0
        },
        {
            "date": "2004-09-07 02:43:50",
            "SQALE_INDEX": 37949.0
        },
        {
            "date": "2004-09-08 22:26:33",
            "SQALE_INDEX": 37818.0
        },
        {
            "date": "2004-09-13 03:09:29",
            "SQALE_INDEX": 38316.0
        },
        {
            "date": "2004-09-16 01:13:13",
            "SQALE_INDEX": 38231.0
        },
        {
            "date": "2004-10-26 16:42:56",
            "SQALE_INDEX": 39076.0
        },
        {
            "date": "2004-10-27 21:49:28",
            "SQALE_INDEX": 39266.0
        },
        {
            "date": "2004-10-27 21:51:13",
            "SQALE_INDEX": 39411.0
        },
        {
            "date": "2004-10-28 20:10:50",
            "SQALE_INDEX": 39408.0
        },
        {
            "date": "2004-12-08 10:00:28",
            "SQALE_INDEX": 39435.0
        },
        {
            "date": "2004-12-28 01:39:23",
            "SQALE_INDEX": 39453.0
        },
        {
            "date": "2005-01-06 09:00:36",
            "SQALE_INDEX": 39482.0
        },
        {
            "date": "2005-01-20 05:18:27",
            "SQALE_INDEX": 39251.0
        },
        {
            "date": "2005-01-26 22:46:28",
            "SQALE_INDEX": 39669.0
        },
        {
            "date": "2005-01-27 05:52:27",
            "SQALE_INDEX": 39667.0
        },
        {
            "date": "2005-01-28 12:36:23",
            "SQALE_INDEX": 39756.0
        },
        {
            "date": "2005-01-28 22:29:09",
            "SQALE_INDEX": 39851.0
        },
        {
            "date": "2005-03-03 00:34:58",
            "SQALE_INDEX": 40200.0
        },
        {
            "date": "2005-07-19 17:34:00",
            "SQALE_INDEX": 40800.0
        },
        {
            "date": "2005-11-13 13:33:00",
            "SQALE_INDEX": 40989.0
        },
        {
            "date": "2005-11-14 01:04:40",
            "SQALE_INDEX": 40991.0
        },
        {
            "date": "2005-11-21 00:47:23",
            "SQALE_INDEX": 41103.0
        },
        {
            "date": "2008-11-16 22:46:49",
            "SQALE_INDEX": 42313.0
        },
        {
            "date": "2017-09-01 18:17:20",
            "SQALE_INDEX": 42910.0
        }
    ]
}