{
    "change_points": [
        {
            "date": "2011-05-11 04:54:36",
            "SQALE_INDEX": 32880.0
        },
        {
            "date": "2011-05-25 04:54:36",
            "SQALE_INDEX": 33020.75
        },
        {
            "date": "2011-06-08 04:54:36",
            "SQALE_INDEX": 33161.5
        },
        {
            "date": "2011-06-22 04:54:36",
            "SQALE_INDEX": 33302.25
        },
        {
            "date": "2011-07-06 04:54:36",
            "SQALE_INDEX": 33443.0
        },
        {
            "date": "2011-07-20 04:54:36",
            "SQALE_INDEX": 33583.75
        },
        {
            "date": "2011-08-03 04:54:36",
            "SQALE_INDEX": 33724.5
        },
        {
            "date": "2011-08-17 04:54:36",
            "SQALE_INDEX": 33865.25
        },
        {
            "date": "2011-09-09 17:21:34",
            "SQALE_INDEX": 34006.0
        },
        {
            "date": "2011-09-23 17:21:34",
            "SQALE_INDEX": 27264.5
        },
        {
            "date": "2011-10-09 05:46:51",
            "SQALE_INDEX": 20523.0
        },
        {
            "date": "2011-10-23 11:35:10",
            "SQALE_INDEX": 20444.0
        },
        {
            "date": "2011-11-07 09:45:31",
            "SQALE_INDEX": 26085.0
        },
        {
            "date": "2011-11-21 09:45:31",
            "SQALE_INDEX": 26087.8
        },
        {
            "date": "2011-12-05 09:45:31",
            "SQALE_INDEX": 26090.6
        },
        {
            "date": "2011-12-19 09:45:31",
            "SQALE_INDEX": 26093.4
        }
    ]
}